<?xml version="1.0" encoding="utf-8"?>
<!DOCTYPE hibernate-mapping PUBLIC "-//Hibernate/Hibernate Mapping DTD 3.0//EN"
"http://hibernate.sourceforge.net/hibernate-mapping-3.0.dtd">
<!-- Mapping file autogenerated by MyEclipse Persistence Tools -->
<hibernate-mapping>
	<class name="com.ssxt.entity.mysql.RtuGroundWater" table="RTU_GroundWater" >
		<id name="id" type="java.lang.Integer">
			<column name="ID" />
			<generator class="identity" />
		</id>
		<property name="yczid" type="java.lang.String">
			<column name="YCZID" length="50" not-null="true" />
		</property>
		<property name="functioncode" type="java.lang.String">
			<column name="FUNCTIONCODE" length="5" />
		</property>
		<property name="tt" type="java.sql.Timestamp">
			<column name="TT" length="23" not-null="true" />
		</property>
		<property name="insertdt" type="java.sql.Timestamp">
			<column name="INSERTDT" length="23" />
		</property>
		<property name="ff0e1" type="java.lang.String">
			<column name="FF0E1" length="50" />
		</property>
		<property name="ff0e2" type="java.lang.String">
			<column name="FF0E2" length="50" />
		</property>
		<property name="ff0e3" type="java.lang.String">
			<column name="FF0E3" length="50" />
		</property>
		<property name="ff0e4" type="java.lang.String">
			<column name="FF0E4" length="50" />
		</property>
		<property name="ff0e5" type="java.lang.String">
			<column name="FF0E5" length="50" />
		</property>
		<property name="ff0e6" type="java.lang.String">
			<column name="FF0E6" length="50" />
		</property>
		<property name="ff031" type="java.lang.String">
			<column name="FF031" length="50" />
		</property>
		<property name="ff032" type="java.lang.String">
			<column name="FF032" length="50" />
		</property>
		<property name="ff033" type="java.lang.String">
			<column name="FF033" length="50" />
		</property>
		<property name="ff034" type="java.lang.String">
			<column name="FF034" length="50" />
		</property>
		<property name="ff035" type="java.lang.String">
			<column name="FF035" length="50" />
		</property>
		<property name="ff036" type="java.lang.String">
			<column name="FF036" length="50" />
		</property>
		<property name="vt" type="java.lang.String">
			<column name="VT" length="50" />
		</property>
	</class>
</hibernate-mapping>
